sber_ld_dbtools/__init__.py
sber_ld_dbtools/credentials/__init__.py
sber_ld_dbtools/credentials/_core.py
sber_ld_dbtools/loader/__init__.py
sber_ld_dbtools/loader/config.py
sber_ld_dbtools/loader/greenplum/__init__.py
sber_ld_dbtools/loader/greenplum/_core.py
sber_ld_dbtools/loader/oracle/__init__.py
sber_ld_dbtools/loader/oracle/_core.py
sber_ld_dbtools/loader/spark/__init__.py
sber_ld_dbtools/loader/spark/_core.py
sber_ld_dbtools/loader/spark/hive/__init__.py
sber_ld_dbtools/loader/spark/hive/_core.py
sber_ld_dbtools/loader/teradata/__init__.py
sber_ld_dbtools/loader/teradata/_core.py
sber_ld_dbtools/py.typed
sber_ld_dbtools-0.0.9.dist-info/LICENSE
sber_ld_dbtools-0.0.9.dist-info/WHEEL
sber_ld_dbtools-0.0.9.dist-info/METADATA
sber_ld_dbtools-0.0.9.dist-info/RECORD
