Metadata-Version: 2.1
Name: sber-ld-dbtools
Version: 0.0.9
Summary: Tools for interacting with LD databases.
Home-page: https://github.com/andrewsonin/sber_ld_dbtools
License: Apache-2.0
Author: Andrew Sonin
Author-email: sonin.cel@yandex.ru
Requires-Python: >=3.7,<4.0
Classifier: License :: OSI Approved :: Apache Software License
Classifier: Programming Language :: Python :: 3
Classifier: Programming Language :: Python :: 3.10
Classifier: Programming Language :: Python :: 3.7
Classifier: Programming Language :: Python :: 3.8
Classifier: Programming Language :: Python :: 3.9
Requires-Dist: JPype1 (>=1,<2)
Requires-Dist: JayDeBeApi (>=1,<2)
Requires-Dist: pandakeeper (>=0.0.27,<0.0.28)
Requires-Dist: pandas (>=1,<2)
Requires-Dist: psycopg2-binary (>=2,<3)
Requires-Dist: pyspark (>=2,<3)
Requires-Dist: teradatasql (>=17,<18)
Requires-Dist: varutils (>=0.0.8,<0.0.9)
Project-URL: Repository, https://github.com/andrewsonin/sber_ld_dbtools
